choumine_review_classifier/__init__.py
choumine_review_classifier/__main__.py
choumine_review_classifier/analyze_reviews.py
choumine_review_classifier/common.py
choumine_review_classifier/review_classifier.py
choumine_review_classifier/select_column.py
choumine_review_classifier/terminal_monitor.py
choumine_review_classifier/tools.py
choumine_review_classifier-0.1.1.dist-info/METADATA
choumine_review_classifier-0.1.1.dist-info/WHEEL
choumine_review_classifier-0.1.1.dist-info/entry_points.txt
choumine_review_classifier-0.1.1.dist-info/RECORD
