Metadata-Version: 2.4
Name: choumine-review-classifier
Version: 0.1.1
Summary: Add your description here
Author-email: choumine <569908115@qq.com>
Requires-Python: >=3.13
Requires-Dist: mcp[cli]>=1.6.0
Requires-Dist: openai>=1.76.2
Requires-Dist: pandas>=2.2.3
Requires-Dist: pyyaml>=6.0.2
